ghmeister/__init__.py
ghmeister/__main__.py
ghmeister/auth.py
ghmeister/services/GitHubService.py
ghmeister/services/__init__.py
ghmeister/tui/GHMeisterApp.py
ghmeister/tui/__init__.py
ghmeister-0.1.0.dist-info/LICENSE
ghmeister-0.1.0.dist-info/METADATA
ghmeister-0.1.0.dist-info/WHEEL
ghmeister-0.1.0.dist-info/entry_points.txt
ghmeister-0.1.0.dist-info/RECORD
