Metadata-Version: 2.1
Name: ghmeister
Version: 0.1.0
Summary: GitHub Manager
License: MIT
Author: Rob van der Leek
Author-email: 5324924+robvanderleek@users.noreply.github.com
Requires-Python: >=3.11,<3.13
Classifier: License :: OSI Approved :: MIT License
Classifier: Programming Language :: Python :: 3
Classifier: Programming Language :: Python :: 3.11
Classifier: Programming Language :: Python :: 3.12
Requires-Dist: pygithub (>=2.1.1,<3.0.0)
Requires-Dist: pyyaml (>=6.0.1,<7.0.0)
Requires-Dist: requests (>=2.31.0,<3.0.0)
Requires-Dist: textual (>=0.42.0,<0.43.0)
Requires-Dist: typer (>=0.9.0,<0.10.0)
